atooms/__init__.py
atooms/models/__init__.py
atooms/models/_schemas.py
atooms/models/helpers.py
atooms/models/_v1/bernu_hiwatari_hansen_pastore.json
atooms/models/_v1/coslovich_dirindin.json
atooms/models/_v1/coslovich_pastore.json
atooms/models/_v1/dellavalle_gazzillo_frattini_pastore.json
atooms/models/_v1/gaussian_core.json
atooms/models/_v1/grigera_cavagna_giardina_parisi.json
atooms/models/_v1/harmonic_spheres.json
atooms/models/_v1/kob_andersen.json
atooms/models/_v1/lennard_jones.json
atooms/models/_v1/roux_barrat_hansen.json
atooms/models/_v1/wahnstrom.json
atooms/models/_v2/coslovich_pastore.json
atooms/models/_v2/dellavalle_gazzillo_frattini_pastore.json
atooms/models/_v2/kob_andersen.json
atooms/models/f90/__init__.py
atooms/models/f90/cubic_spline.f90
atooms/models/f90/cut.f90
atooms/models/f90/cut_shift.f90
atooms/models/f90/fene.f90
atooms/models/f90/gaussian.f90
atooms/models/f90/harmonic.f90
atooms/models/f90/harmonic_bending.f90
atooms/models/f90/harmonic_potential.f90
atooms/models/f90/helpers.f90
atooms/models/f90/helpers.py
atooms/models/f90/helpers_3d.f90
atooms/models/f90/interaction.f90
atooms/models/f90/interaction.py
atooms/models/f90/interaction_bonds.f90
atooms/models/f90/interaction_molecular_three_body.f90
atooms/models/f90/interaction_molecular_two_body.f90
atooms/models/f90/interaction_three_body.f90
atooms/models/f90/inverse_power.f90
atooms/models/f90/inverse_power_exp.f90
atooms/models/f90/lennard_jones.f90
atooms/models/f90/linear_cut_shift.f90
atooms/models/f90/neighbor_list.f90
atooms/models/f90/neighbor_list.py
atooms/models/f90/quadratic_cut_shift.f90
atooms/models/f90/sum_inverse_power.f90
atooms/models/f90/trajectory.py
atooms/models/f90/verlet_list.py
atooms/models/f90/yukawa.f90
atooms/models/rumd/__init__.py
atooms/models/rumd/interaction.py
atooms/models/samples/_db.json
atooms/models/samples/bernu_hiwatari_hansen_pastore_N216_rho0.5342_T0.208.xyz
atooms/models/samples/coslovich_pastore_N300_rho1.655_T0.31.xyz
atooms_models-2.0.0.dist-info/LICENSE
atooms_models-2.0.0.dist-info/METADATA
atooms_models-2.0.0.dist-info/WHEEL
atooms_models-2.0.0.dist-info/top_level.txt
atooms_models-2.0.0.dist-info/RECORD
