Metadata-Version: 2.1
Name: atooms-models
Version: 2.0.0
Summary: UNKNOWN
Home-page: https://framagit.org/atooms/models
Author: Daniele Coslovich
Author-email: dcoslovich@units.it
License: GPLv3
Platform: UNKNOWN
Classifier: License :: OSI Approved :: GNU General Public License v3 (GPLv3)
Classifier: Programming Language :: Python
Classifier: Programming Language :: Python :: 2
Classifier: Programming Language :: Python :: 2.7
Classifier: Programming Language :: Python :: 3
Classifier: Programming Language :: Python :: 3.6
Requires-Dist: atooms (~=3.3)
Requires-Dist: f2py-jit (~=0.5)
Requires-Dist: jsonschema
